{
    "id": "rog_phone_9_pro",
    "brandLabel": "ASUS",
    "modelLabel": "ROG Phone 9 Pro",
    "summary": "Snapdragon 8 Elite - Android 15",
    "profile": {
        "brand": "asus",
        "manufacturer": "asus",
        "model": "AI2501",
        "productName": "AI2501",
        "deviceCode": "AI2501",
        "board": "sun",
        "hardware": "qcom",
        "boardPlatform": "sun",
        "buildFingerprint": "asus/AI2501/AI2501:15/AP3A.240905.015/1755566778:user/release-keys",
        "buildId": "AP3A.240905.015",
        "buildDisplayId": "AP3A.240905.015",
        "buildIncremental": "1755566778",
        "buildRelease": "15",
        "buildSdk": 35,
        "securityPatch": "2025-03-01",
        "buildDescription": "AI2501-user 15 AP3A.240905.015 1755566778 release-keys",
        "buildFlavor": "AI2501-user",
        "buildProduct": "AI2501",
        "buildCharacteristics": "nosdcard",
        "screenWidth": 1080,
        "screenHeight": 2400,
        "screenDensity": 420,
        "operatorAlpha": "T-Mobile",
        "operatorNumeric": "310260",
        "simOperatorAlpha": "T-Mobile",
        "simOperatorNumeric": "310260",
        "simCountryIso": "us",
        "timezone": "America/Los_Angeles",
        "socModel": "Snapdragon 8 Elite",
        "socManufacturer": "Qualcomm"
    }
}